{"collections_config":{"pages":{"output":true,"filter":"strict","parse_branch_index":true,"auto_discovered":true,"path":"content"},"posts":{"path":"content/posts","output":true},"data":{"output":false,"auto_discovered":false,"path":"data"}},"_inputs":{"type":{"hidden":true},"large_header":{"comment":"Toggles the size of the top banner."},"show_in_navigation":{"comment":"Toggles a link in the top banner."},"author_staff_member":{"comment":"The staff member writing this post."},"call_to_action":{"type":"select","comment":"Type of request shown at the bottom of this page.","options":{"values":["Contact","Blog","Map"]}},"background_image_path":{"comment":"Image shown in the top banner, blank for the default."},"testimonials":{"comment":"Update, add or remove testimonials."},"map":{"comment":"Update the map location and display settings."},"latitude":{"comment":"Coordinates for the center marker on the map."},"longitude":{"comment":"Coordinates for the center marker on the map."},"zoom":{"comment":"The zoom level for the map."},"phone_extension":{"comment":"The digits after dialing the company phone."},"credentials":{"comment":"Shown as subtext on staff member summaries."},"contact_email_address":{"comment":"Address for the contact form to send to."},"new_window":{"comment":"Whether the link opens a new browser tab/window."}},"base_url":"","source":"","paths":{"source":"","archetypes":"archetypes","assets":"assets","content":"content","pages":"content","data":"data","layouts":"layouts","publish":"public","static":"static","uploads":"static/uploads","config":""},"time":"2022-07-20T23:31:01.880Z","version":"0.0.3","cloudcannon":{"name":"cloudcannon-hugo","version":"1.0.0"},"generator":{"name":"hugo","version":"0.101.0","metadata":{"markdown":"goldmark","goldmark":{"extensions":{"definitionList":true,"footnote":true,"linkify":true,"strikethrough":true,"table":true,"taskList":true,"typographer":true},"parser":{"attribute":true,"autoHeadingID":true,"autoHeadingIDType":"github"},"renderer":{"hardWraps":false,"unsafe":true,"xhtml":false}}}},"collections":{"pages":[{"url":"/","path":"content/_index.md","collection":"pages","title":"Home","call_to_action":"Contact","large_header":true,"menu":{"footer":{"weight":1}},"testimonials":[{"message":"We use Justice Law in all our endeavours. They offer an unparalleled service when it comes to running a business.","image":"https://placekitten.com/g/60/60?a=.png","name":"Joice Carmold"},{"message":"Justice Law are the best of the best. Being local, they care about people and have strong ties to the community.","image":"https://www.fillmurray.com/60/60?a=.png","name":"Peter Rottenburg"},{"message":"Justice Law were everything we could have hoped for when buying our first home. Highly recommended to all.","image":"https://placebear.com/60/60?a=.png","name":"D. and G. Gibbleston"}],"_inputs":{"image":{"options":{"width":60,"height":60}}},"content_path":"_index.md","layout":"index"},{"url":"/about/","path":"content/about.md","collection":"pages","title":"About","call_to_action":"Contact","large_header":false,"type":"about","menu":{"main":{"weight":1},"footer":{"weight":2}},"content_path":"about.md","layout":"_default/single"},{"url":"/contact/","path":"content/contact.md","collection":"pages","title":"Contact","call_to_action":"Map","large_header":false,"type":"contact","menu":{"main":{"weight":3},"footer":{"weight":4}},"map":{"latitude":-45.8787605,"longitude":170.5027976,"zoom":13},"content_path":"contact.md","layout":"_default/single"},{"url":"/contact-success/","path":"content/contact-success.md","collection":"pages","title":"Contact Success","call_to_action":"Blog","large_header":false,"content_path":"contact-success.md","layout":"_default/single"},{"url":"/posts/","path":"content/posts/_index.md","collection":"pages","title":"Blog","call_to_action":"Contact","large_header":false,"menu":{"main":{"weight":4},"footer":{"weight":5}},"content_path":"posts/_index.md","layout":"_default/list"},{"url":"/services/","path":"content/services.md","collection":"pages","title":"Services","call_to_action":"Contact","large_header":false,"menu":{"main":{"weight":2},"footer":{"weight":3}},"content_path":"services.md","layout":"_default/single"},{"url":"/terms/","path":"content/terms.md","collection":"pages","title":"Terms","call_to_action":"Contact","large_header":false,"content_path":"terms.md","layout":"_default/single"}],"posts":[{"url":"/posts/1/01/01/","path":"content/posts/_defaults.md","collection":"posts","title":null,"date":null,"categories":null,"author":null,"image":null,"draft":true,"content_path":"posts/_defaults.md","layout":"posts/single","published":false},{"url":"/posts/2020/11/11/real-estate-flipping/","path":"content/posts/real-estate-flipping.md","collection":"posts","title":"Real Estate Flipping","date":"2020-11-10T11:00:00.000Z","categories":["Property"],"author":"john-doe","image":"https://unsplash.it/600/450?image=448&a=.png","draft":false,"content_path":"posts/real-estate-flipping.md","layout":"posts/single"},{"url":"/posts/2020/08/10/business-mergers/","path":"content/posts/business-mergers.md","collection":"posts","title":"Business Mergers","date":"2020-08-09T11:00:00.000Z","categories":["Business"],"author":"jane-doe","image":"https://unsplash.it/600/450?image=737&a=.png","draft":false,"content_path":"posts/business-mergers.md","layout":"posts/single"}],"data":[]},"files":{"/.cloudcannon/prebuild":"dbe513881b777d11417d6796770ad708","/cloudcannon.config.yml":"7417a73bbba4574d43532647fd8597bc","/LICENSE":"de429ee7c82ea71dbe65666994bf32a4","/siteicon.png":"ebe261111cc42d710ab808346074b860","/archetypes/default.md":"ad09f97583de43ecc8fe43b16f728cf0","/archetypes/posts.md":"3a4738fb0fe926a80f1c33f4adbea218","/content/posts/_defaults.md":"bb2b5b9760c7c5479d88b577f029b645","/content/posts/real-estate-flipping.md":"231c1e65479d81d8cf95d5508f260018","/content/posts/business-mergers.md":"e6b77c786da456ae792098791b358a4a","/content/posts/_index.md":"b908549de11f6ea81363bf58a3897cb0","/content/contact.md":"83d7ffc0cecdff791b65d2ba33e092d5","/content/terms.md":"28b5ccf55d823033713c0ebbae860592","/content/services.md":"b339179023ec68c5debf5d1394b4a8f8","/content/contact-success.md":"96d30649aaa8529a280b5351ae22db25","/content/about.md":"3b28a907a854969db4ccb4aaa8ea73a7","/content/_index.md":"4081bac33fe3092b8af5acf595c59145","/README.md":"96b50f78677ee489a07721159d5fe560","/layouts/page/single.html":"74e6bada5b02a46effc58b9a6c079a24","/layouts/contact/single.html":"858ff4e4fb4ceaa92ed5349b53bbc8d2","/layouts/index.html":"0f5bd852dc20c47db4f21c350cfb9121","/layouts/posts/single.html":"4af5254bbbf64e85c69725e826aaca3a","/layouts/posts/summary-details.html":"0990f5edee44f1049d82a13a6d5107f5","/layouts/posts/summary.html":"3cfdfc127e4acdbccd8eb31b5ebe8602","/layouts/about/single.html":"b4520d0abb943dbc0dad5b8c6b0994c1","/layouts/_default/single.html":"74e6bada5b02a46effc58b9a6c079a24","/layouts/_default/list.html":"7e3203accb985f88149eff949cf9ca69","/layouts/_default/taxonomy.html":"4b2ee82d3e1db59a8e940362323982e3","/layouts/_default/baseof.html":"5a19f26175e381d5ef80b6bebf40191b","/layouts/partials/site-header.html":"06e6eed613d9b1f12dee5227ec706086","/layouts/partials/site-footer.html":"2b24366dbb8c52cb3b84780760caf92f","/layouts/partials/social-icon.html":"be266d1b248f26e73bed14b016e2be9c","/layouts/partials/disqus.html":"893cae23a4ffbdff43bc4a540ff89fe8","/layouts/partials/page-header.html":"a9e7c7ab6121fc0ce9ec9430b452781d","/layouts/partials/staff-member.html":"9b1ef9e502c6c9680a8963e88535348d","/static/apple-touch-icon.png":"6bb02fefc4d1325e409104c5e01cb1b1","/static/images/_screenshot.png":"6fa934c2c94e821ea0285e5e06336b42","/static/images/favicon.png":"e3dc9d192120cd60c3cf7ecc7bd04bf2","/static/uploads/building.jpg":"414db6159593b21e7de651e0713a0211","/static/touch-icon.png":"5b37c2bb51b0ee0e045180d23823a05b","/config.toml":"f59beae1e3de51ba59dafc0761d4d883","/data/authors/default.yml":"b32dad9fe119be3cd5716ed422f8171c","/data/authors/jane-doe.yml":"2237071f465c6c22ad33ba6c1c19d085","/data/authors/john-doe.yml":"6544b4174b3b464aa7236e66bdc9ac52","/data/company.yml":"1e06c14f877caea9ff1fb47a7fa5f705","/assets/sass/cloudcannon.scss":"ce97f3028e059b33226b7556277fd3b8","/assets/sass/forms.scss":"81cf38ce3272982c92752660b6b2ff52","/assets/sass/layout.scss":"99959150cb92bba39d4824c7e0dd2b18","/assets/sass/main.scss":"a2d4050a260193606d3da8c03dfef3aa","/assets/sass/typography.scss":"3f145f0eacc81467899e88884f41eecb","/.cloudcannon/routing.json":"f34f1741b5719f0bdf2c67376b5b642d"}}